Metadata-Version: 2.1
Name: jishkucord
Version: 2.5.0
Summary: A py-cord extension including useful tools for bot development and debugging.
Home-page: https://github.com/Sengolda/jishkucord/
Author: Devon (Gorialis) R & Sengolda
License: MIT
Download-URL: https://github.com/Sengolda/jishkucord/archive/2.5.0.tar.gz
Project-URL: Documentation, https://jishkucord.readthedocs.io/en/latest/
Project-URL: Code, https://github.com/Sengolda/jishkucord/
Project-URL: Issue tracker, https://github.com/Sengolda/jishkucord/issues/
Keywords: jishkucord discord.py discord cog repl extension
Platform: UNKNOWN
Classifier: Development Status :: 5 - Production/Stable
Classifier: Framework :: AsyncIO
Classifier: Intended Audience :: Developers
Classifier: License :: OSI Approved :: MIT License
Classifier: Natural Language :: English
Classifier: Operating System :: OS Independent
Classifier: Programming Language :: Python :: 3 :: Only
Classifier: Programming Language :: Python :: 3.8
Classifier: Programming Language :: Python :: 3.9
Classifier: Topic :: Communications :: Chat
Classifier: Topic :: Internet
Classifier: Topic :: Software Development :: Debuggers
Classifier: Topic :: Software Development :: Testing
Classifier: Topic :: Utilities
Requires-Python: >=3.8.0
License-File: LICENSE
Requires-Dist: braceexpand (>=0.1.7)
Requires-Dist: click (>=8.0.1)
Requires-Dist: import-expression (<2.0.0,>=1.0.0)
Provides-Extra: docs
Requires-Dist: sphinx (>=3.5.4) ; extra == 'docs'
Requires-Dist: sphinxcontrib-asyncio ; extra == 'docs'
Provides-Extra: procinfo
Requires-Dist: psutil ; extra == 'procinfo'
Provides-Extra: publish
Requires-Dist: Jinja2 ; extra == 'publish'
Provides-Extra: test
Requires-Dist: click ; extra == 'test'
Requires-Dist: coverage ; extra == 'test'
Requires-Dist: flake8 ; extra == 'test'
Requires-Dist: isort ; extra == 'test'
Requires-Dist: pylint ; extra == 'test'
Requires-Dist: pytest ; extra == 'test'
Requires-Dist: pytest-cov ; extra == 'test'
Requires-Dist: pytest-mock ; extra == 'test'
Provides-Extra: voice
Requires-Dist: youtube-dl ; extra == 'voice'
